odoo/addons/mrp_production_back_to_draft/README.rst
odoo/addons/mrp_production_back_to_draft/__init__.py
odoo/addons/mrp_production_back_to_draft/__manifest__.py
odoo/addons/mrp_production_back_to_draft/i18n/mrp_production_back_to_draft.pot
odoo/addons/mrp_production_back_to_draft/models/__init__.py
odoo/addons/mrp_production_back_to_draft/models/mrp_production.py
odoo/addons/mrp_production_back_to_draft/readme/CONTRIBUTORS.rst
odoo/addons/mrp_production_back_to_draft/readme/DESCRIPTION.rst
odoo/addons/mrp_production_back_to_draft/static/description/icon.png
odoo/addons/mrp_production_back_to_draft/static/description/index.html
odoo/addons/mrp_production_back_to_draft/tests/__init__.py
odoo/addons/mrp_production_back_to_draft/tests/test_mrp_return_to_draft.py
odoo/addons/mrp_production_back_to_draft/views/mrp_production_views.xml
odoo14_addon_mrp_production_back_to_draft-14.0.1.0.1.dist-info/METADATA
odoo14_addon_mrp_production_back_to_draft-14.0.1.0.1.dist-info/WHEEL
odoo14_addon_mrp_production_back_to_draft-14.0.1.0.1.dist-info/top_level.txt
odoo14_addon_mrp_production_back_to_draft-14.0.1.0.1.dist-info/RECORD
